{"2016-06-01": {"usd": {"purchase": 5694.15, "sale": 5708.02}, "brl": {"purchase": 1580.87, "sale": 1584.81}, "arp": {"purchase": 409.12, "sale": 410.24}, "jpy": {"purchase": 51.93, "sale": 52.07}, "eur": {"purchase": 6366.06, "sale": 6382.14}, "gbp": {"purchase": 8210.39, "sale": 8230.96}}, "2016-06-02": {"usd": {"purchase": 5686.76, "sale": 5699.03}, "brl": {"purchase": 1586.26, "sale": 1589.69}, "arp": {"purchase": 408.77, "sale": 409.83}, "jpy": {"purchase": 52.28, "sale": 52.4}, "eur": {"purchase": 6345.86, "sale": 6360.12}, "gbp": {"purchase": 8209.98, "sale": 8228.26}}, "2016-06-03": {"usd": {"purchase": 5678.15, "sale": 5684.88}, "brl": {"purchase": 1606.77, "sale": 1608.85}, "arp": {"purchase": 409.32, "sale": 410.05}, "jpy": {"purchase": 53.24, "sale": 53.3}, "eur": {"purchase": 6436.18, "sale": 6444.38}, "gbp": {"purchase": 8248.65, "sale": 8258.99}}, "2016-06-04": {"usd": {"purchase": 5678.15, "sale": 5684.88}, "brl": {"purchase": 1606.77, "sale": 1608.85}, "arp": {"purchase": 409.32, "sale": 410.05}, "jpy": {"purchase": 53.24, "sale": 53.3}, "eur": {"purchase": 6436.18, "sale": 6444.38}, "gbp": {"purchase": 8248.65, "sale": 8258.99}}, "2016-06-05": {"usd": {"purchase": 5678.15, "sale": 5684.88}, "brl": {"purchase": 1606.77, "sale": 1608.85}, "arp": {"purchase": 409.32, "sale": 410.05}, "jpy": {"purchase": 53.24, "sale": 53.3}, "eur": {"purchase": 6436.18, "sale": 6444.38}, "gbp": {"purchase": 8248.65, "sale": 8258.99}}, "2016-06-06": {"usd": {"purchase": 5638.89, "sale": 5649.03}, "brl": {"purchase": 1612.77, "sale": 1615.86}, "arp": {"purchase": 409.8, "sale": 410.66}, "jpy": {"purchase": 52.69, "sale": 52.79}, "eur": {"purchase": 6414.8, "sale": 6426.9}, "gbp": {"purchase": 8156.09, "sale": 8171.32}}, "2016-06-07": {"usd": {"purchase": 5609.81, "sale": 5633.27}, "brl": {"purchase": 1624.81, "sale": 1631.65}, "arp": {"purchase": 405.9, "sale": 407.79}, "jpy": {"purchase": 52.24, "sale": 52.46}, "eur": {"purchase": 6368.26, "sale": 6395.45}, "gbp": {"purchase": 8165.64, "sale": 8200.35}}, "2016-06-08": {"usd": {"purchase": 5631.29, "sale": 5641.79}, "brl": {"purchase": 1665.37, "sale": 1668.67}, "arp": {"purchase": 408.82, "sale": 409.78}, "jpy": {"purchase": 52.74, "sale": 52.84}, "eur": {"purchase": 6422.49, "sale": 6435.03}, "gbp": {"purchase": 8182.26, "sale": 8198.09}}, "2016-06-09": {"usd": {"purchase": 5643.18, "sale": 5656.31}, "brl": {"purchase": 1670.91, "sale": 1675.2}, "arp": {"purchase": 406.83, "sale": 407.9}, "jpy": {"purchase": 52.91, "sale": 53.04}, "eur": {"purchase": 6386.39, "sale": 6401.81}, "gbp": {"purchase": 8163.42, "sale": 8182.98}}, "2016-06-10": {"usd": {"purchase": 5662.5, "sale": 5674.98}, "brl": {"purchase": 1650.3, "sale": 1654.13}, "arp": {"purchase": 410.09, "sale": 411.11}, "jpy": {"purchase": 52.87, "sale": 52.99}, "eur": {"purchase": 6380.51, "sale": 6395.13}, "gbp": {"purchase": 8122.29, "sale": 8140.76}}, "2016-06-11": {"usd": {"purchase": 5662.5, "sale": 5674.98}, "brl": {"purchase": 1650.3, "sale": 1654.13}, "arp": {"purchase": 410.09, "sale": 411.11}, "jpy": {"purchase": 52.87, "sale": 52.99}, "eur": {"purchase": 6380.51, "sale": 6395.13}, "gbp": {"purchase": 8122.29, "sale": 8140.76}}, "2016-06-12": {"usd": {"purchase": 5662.5, "sale": 5674.98}, "brl": {"purchase": 1650.3, "sale": 1654.13}, "arp": {"purchase": 410.09, "sale": 411.11}, "jpy": {"purchase": 52.87, "sale": 52.99}, "eur": {"purchase": 6380.51, "sale": 6395.13}, "gbp": {"purchase": 8122.29, "sale": 8140.76}}, "2016-06-13": {"usd": {"purchase": 5647.28, "sale": 5661.49}, "brl": {"purchase": 1626.66, "sale": 1630.94}, "arp": {"purchase": 409.02, "sale": 410.16}, "jpy": {"purchase": 53.25, "sale": 53.39}, "eur": {"purchase": 6375.21, "sale": 6391.82}, "gbp": {"purchase": 8034.39, "sale": 8055.17}}, "2016-06-14": {"usd": {"purchase": 5644.16, "sale": 5651.97}, "brl": {"purchase": 1615.48, "sale": 1617.99}, "arp": {"purchase": 410.45, "sale": 411.14}, "jpy": {"purchase": 53.23, "sale": 53.31}, "eur": {"purchase": 6327.67, "sale": 6336.99}, "gbp": {"purchase": 7966.17, "sale": 7977.76}}, "2016-06-15": {"usd": {"purchase": 5650.64, "sale": 5662.69}, "brl": {"purchase": 1633.84, "sale": 1637.33}, "arp": {"purchase": 410.96, "sale": 411.95}, "jpy": {"purchase": 53.35, "sale": 53.47}, "eur": {"purchase": 6350.75, "sale": 6364.86}, "gbp": {"purchase": 8003.0, "sale": 8020.63}}, "2016-06-16": {"usd": {"purchase": 5634.21, "sale": 5644.61}, "brl": {"purchase": 1619.72, "sale": 1623.04}, "arp": {"purchase": 405.6, "sale": 406.47}, "jpy": {"purchase": 54.06, "sale": 54.17}, "eur": {"purchase": 6326.65, "sale": 6338.9}, "gbp": {"purchase": 7999.45, "sale": 8014.78}}, "2016-06-17": {"usd": {"purchase": 5621.79, "sale": 5637.43}, "brl": {"purchase": 1642.98, "sale": 1647.75}, "arp": {"purchase": 404.18, "sale": 405.42}, "jpy": {"purchase": 53.95, "sale": 54.1}, "eur": {"purchase": 6343.07, "sale": 6361.28}, "gbp": {"purchase": 8054.34, "sale": 8077.31}}, "2016-06-18": {"usd": {"purchase": 5621.79, "sale": 5637.43}, "brl": {"purchase": 1642.98, "sale": 1647.75}, "arp": {"purchase": 404.18, "sale": 405.42}, "jpy": {"purchase": 53.95, "sale": 54.1}, "eur": {"purchase": 6343.07, "sale": 6361.28}, "gbp": {"purchase": 8054.34, "sale": 8077.31}}, "2016-06-19": {"usd": {"purchase": 5621.79, "sale": 5637.43}, "brl": {"purchase": 1642.98, "sale": 1647.75}, "arp": {"purchase": 404.18, "sale": 405.42}, "jpy": {"purchase": 53.95, "sale": 54.1}, "eur": {"purchase": 6343.07, "sale": 6361.28}, "gbp": {"purchase": 8054.34, "sale": 8077.31}}, "2016-06-20": {"usd": {"purchase": 5576.1, "sale": 5594.0}, "brl": {"purchase": 1638.49, "sale": 1644.23}, "arp": {"purchase": 400.9, "sale": 402.3}, "jpy": {"purchase": 53.59, "sale": 53.76}, "eur": {"purchase": 6307.68, "sale": 6328.49}, "gbp": {"purchase": 8163.41, "sale": 8190.18}}, "2016-06-21": {"usd": {"purchase": 5580.92, "sale": 5589.49}, "brl": {"purchase": 1639.61, "sale": 1642.33}, "arp": {"purchase": 400.65, "sale": 401.53}, "jpy": {"purchase": 53.29, "sale": 53.38}, "eur": {"purchase": 6284.67, "sale": 6294.88}, "gbp": {"purchase": 8185.54, "sale": 8198.66}}, "2016-06-22": {"usd": {"purchase": 5623.77, "sale": 5642.22}, "brl": {"purchase": 1663.54, "sale": 1669.15}, "arp": {"purchase": 399.9, "sale": 401.32}, "jpy": {"purchase": 53.88, "sale": 54.06}, "eur": {"purchase": 6361.05, "sale": 6382.48}, "gbp": {"purchase": 8247.82, "sale": 8275.44}}, "2016-06-23": {"usd": {"purchase": 5636.42, "sale": 5653.09}, "brl": {"purchase": 1680.31, "sale": 1686.28}, "arp": {"purchase": 394.76, "sale": 396.03}, "jpy": {"purchase": 53.28, "sale": 53.44}, "eur": {"purchase": 6406.35, "sale": 6425.87}, "gbp": {"purchase": 8360.5, "sale": 8385.79}}, "2016-06-24": {"usd": {"purchase": 5640.24, "sale": 5668.42}, "brl": {"purchase": 1669.6, "sale": 1678.19}, "arp": {"purchase": 378.35, "sale": 380.37}, "jpy": {"purchase": 55.16, "sale": 55.44}, "eur": {"purchase": 6291.12, "sale": 6323.69}, "gbp": {"purchase": 7747.43, "sale": 7787.28}}, "2016-06-25": {"usd": {"purchase": 5640.24, "sale": 5668.42}, "brl": {"purchase": 1669.6, "sale": 1678.19}, "arp": {"purchase": 378.35, "sale": 380.37}, "jpy": {"purchase": 55.16, "sale": 55.44}, "eur": {"purchase": 6291.12, "sale": 6323.69}, "gbp": {"purchase": 7747.43, "sale": 7787.28}}, "2016-06-26": {"usd": {"purchase": 5640.24, "sale": 5668.42}, "brl": {"purchase": 1669.6, "sale": 1678.19}, "arp": {"purchase": 378.35, "sale": 380.37}, "jpy": {"purchase": 55.16, "sale": 55.44}, "eur": {"purchase": 6291.12, "sale": 6323.69}, "gbp": {"purchase": 7747.43, "sale": 7787.28}}, "2016-06-27": {"usd": {"purchase": 5617.87, "sale": 5627.42}, "brl": {"purchase": 1651.73, "sale": 1654.59}, "arp": {"purchase": 369.63, "sale": 370.37}, "jpy": {"purchase": 55.14, "sale": 55.24}, "eur": {"purchase": 6189.21, "sale": 6200.29}, "gbp": {"purchase": 7416.15, "sale": 7429.32}}, "2016-06-28": {"usd": {"purchase": 5601.85, "sale": 5609.26}, "brl": {"purchase": 1691.94, "sale": 1694.33}, "arp": {"purchase": 374.23, "sale": 374.83}, "jpy": {"purchase": 54.53, "sale": 54.61}, "eur": {"purchase": 6188.92, "sale": 6197.67}, "gbp": {"purchase": 7474.55, "sale": 7485.0}}, "2016-06-29": {"usd": {"purchase": 5608.33, "sale": 5621.05}, "brl": {"purchase": 1723.04, "sale": 1727.43}, "arp": {"purchase": 375.94, "sale": 376.9}, "jpy": {"purchase": 54.6, "sale": 54.73}, "eur": {"purchase": 6224.12, "sale": 6238.8}, "gbp": {"purchase": 7552.74, "sale": 7570.43}}, "2016-06-30": {"usd": {"purchase": 5580.0, "sale": 5597.92}, "brl": {"purchase": 1742.55, "sale": 1748.64}, "arp": {"purchase": 370.85, "sale": 372.14}, "jpy": {"purchase": 54.06, "sale": 54.24}, "eur": {"purchase": 6164.78, "sale": 6185.14}, "gbp": {"purchase": 7389.59, "sale": 7413.89}}}