{"2014-12-01": {"usd": {"purchase": 4627.67, "sale": 4632.9}, "brl": {"purchase": 1796.73, "sale": 1799.32}, "arp": {"purchase": 542.45, "sale": 543.42}, "jpy": {"purchase": 38.99, "sale": 39.04}, "eur": {"purchase": 5763.3, "sale": 5770.28}, "gbp": {"purchase": 7243.69, "sale": 7252.34}}, "2014-12-02": {"usd": {"purchase": 4620.98, "sale": 4626.63}, "brl": {"purchase": 1801.83, "sale": 1804.95}, "arp": {"purchase": 541.61, "sale": 542.65}, "jpy": {"purchase": 39.06, "sale": 39.12}, "eur": {"purchase": 5767.45, "sale": 5774.96}, "gbp": {"purchase": 7267.88, "sale": 7277.23}}, "2014-12-03": {"usd": {"purchase": 4627.41, "sale": 4632.54}, "brl": {"purchase": 1799.01, "sale": 1801.42}, "arp": {"purchase": 542.07, "sale": 543.04}, "jpy": {"purchase": 38.85, "sale": 38.89}, "eur": {"purchase": 5739.38, "sale": 5746.2}, "gbp": {"purchase": 7241.43, "sale": 7249.93}}, "2014-12-04": {"usd": {"purchase": 4646.88, "sale": 4656.88}, "brl": {"purchase": 1816.61, "sale": 1821.37}, "arp": {"purchase": 543.62, "sale": 545.26}, "jpy": {"purchase": 38.84, "sale": 38.93}, "eur": {"purchase": 5722.63, "sale": 5735.41}, "gbp": {"purchase": 7300.71, "sale": 7316.89}}, "2014-12-05": {"usd": {"purchase": 4650.28, "sale": 4657.3}, "brl": {"purchase": 1799.37, "sale": 1803.06}, "arp": {"purchase": 544.16, "sale": 545.29}, "jpy": {"purchase": 38.89, "sale": 38.95}, "eur": {"purchase": 5787.74, "sale": 5796.94}, "gbp": {"purchase": 7309.31, "sale": 7320.81}}, "2014-12-06": {"usd": {"purchase": 4650.28, "sale": 4657.3}, "brl": {"purchase": 1799.37, "sale": 1803.06}, "arp": {"purchase": 544.16, "sale": 545.29}, "jpy": {"purchase": 38.89, "sale": 38.95}, "eur": {"purchase": 5787.74, "sale": 5796.94}, "gbp": {"purchase": 7309.31, "sale": 7320.81}}, "2014-12-07": {"usd": {"purchase": 4650.28, "sale": 4657.3}, "brl": {"purchase": 1799.37, "sale": 1803.06}, "arp": {"purchase": 544.16, "sale": 545.29}, "jpy": {"purchase": 38.89, "sale": 38.95}, "eur": {"purchase": 5787.74, "sale": 5796.94}, "gbp": {"purchase": 7309.31, "sale": 7320.81}}, "2014-12-08": {"usd": {"purchase": 4650.28, "sale": 4657.3}, "brl": {"purchase": 1799.37, "sale": 1803.06}, "arp": {"purchase": 544.16, "sale": 545.29}, "jpy": {"purchase": 38.89, "sale": 38.95}, "eur": {"purchase": 5787.74, "sale": 5796.94}, "gbp": {"purchase": 7309.31, "sale": 7320.81}}, "2014-12-09": {"usd": {"purchase": 4632.08, "sale": 4638.4}, "brl": {"purchase": 1778.29, "sale": 1781.6}, "arp": {"purchase": 541.52, "sale": 542.61}, "jpy": {"purchase": 38.14, "sale": 38.19}, "eur": {"purchase": 5693.29, "sale": 5701.52}, "gbp": {"purchase": 7220.95, "sale": 7231.27}}, "2014-12-10": {"usd": {"purchase": 4631.48, "sale": 4635.82}, "brl": {"purchase": 1786.49, "sale": 1789.2}, "arp": {"purchase": 541.91, "sale": 542.89}, "jpy": {"purchase": 38.93, "sale": 38.97}, "eur": {"purchase": 5753.22, "sale": 5759.08}, "gbp": {"purchase": 7269.11, "sale": 7276.38}}, "2014-12-11": {"usd": {"purchase": 4620.39, "sale": 4622.05}, "brl": {"purchase": 1773.12, "sale": 1774.71}, "arp": {"purchase": 539.92, "sale": 540.43}, "jpy": {"purchase": 38.97, "sale": 38.98}, "eur": {"purchase": 5738.52, "sale": 5741.05}, "gbp": {"purchase": 7254.01, "sale": 7257.08}}, "2014-12-12": {"usd": {"purchase": 4616.99, "sale": 4621.38}, "brl": {"purchase": 1745.62, "sale": 1748.01}, "arp": {"purchase": 539.67, "sale": 540.51}, "jpy": {"purchase": 38.68, "sale": 38.72}, "eur": {"purchase": 5723.68, "sale": 5729.59}, "gbp": {"purchase": 7254.68, "sale": 7262.04}}, "2014-12-13": {"usd": {"purchase": 4616.99, "sale": 4621.38}, "brl": {"purchase": 1745.62, "sale": 1748.01}, "arp": {"purchase": 539.67, "sale": 540.51}, "jpy": {"purchase": 38.68, "sale": 38.72}, "eur": {"purchase": 5723.68, "sale": 5729.59}, "gbp": {"purchase": 7254.68, "sale": 7262.04}}, "2014-12-14": {"usd": {"purchase": 4616.99, "sale": 4621.38}, "brl": {"purchase": 1745.62, "sale": 1748.01}, "arp": {"purchase": 539.67, "sale": 540.51}, "jpy": {"purchase": 38.68, "sale": 38.72}, "eur": {"purchase": 5723.68, "sale": 5729.59}, "gbp": {"purchase": 7254.68, "sale": 7262.04}}, "2014-12-15": {"usd": {"purchase": 4621.33, "sale": 4626.59}, "brl": {"purchase": 1729.73, "sale": 1732.48}, "arp": {"purchase": 540.08, "sale": 541.05}, "jpy": {"purchase": 39.04, "sale": 39.09}, "eur": {"purchase": 5762.34, "sale": 5769.36}, "gbp": {"purchase": 7262.42, "sale": 7271.15}}, "2014-12-16": {"usd": {"purchase": 4621.66, "sale": 4630.13}, "brl": {"purchase": 1717.71, "sale": 1722.77}, "arp": {"purchase": 540.2, "sale": 541.55}, "jpy": {"purchase": 39.13, "sale": 39.2}, "eur": {"purchase": 5743.34, "sale": 5754.33}, "gbp": {"purchase": 7217.65, "sale": 7231.34}}, "2014-12-17": {"usd": {"purchase": 4620.71, "sale": 4629.95}, "brl": {"purchase": 1679.59, "sale": 1683.74}, "arp": {"purchase": 540.28, "sale": 541.62}, "jpy": {"purchase": 39.44, "sale": 39.52}, "eur": {"purchase": 5784.2, "sale": 5796.23}, "gbp": {"purchase": 7268.84, "sale": 7283.84}}, "2014-12-18": {"usd": {"purchase": 4633.49, "sale": 4646.19}, "brl": {"purchase": 1719.1, "sale": 1724.58}, "arp": {"purchase": 541.7, "sale": 543.55}, "jpy": {"purchase": 39.49, "sale": 39.6}, "eur": {"purchase": 5750.16, "sale": 5766.39}, "gbp": {"purchase": 7254.19, "sale": 7274.54}}, "2014-12-19": {"usd": {"purchase": 4630.96, "sale": 4639.46}, "brl": {"purchase": 1739.0, "sale": 1742.85}, "arp": {"purchase": 541.37, "sale": 542.72}, "jpy": {"purchase": 39.0, "sale": 39.08}, "eur": {"purchase": 5684.04, "sale": 5694.94}, "gbp": {"purchase": 7248.38, "sale": 7262.15}}, "2014-12-20": {"usd": {"purchase": 4630.96, "sale": 4639.46}, "brl": {"purchase": 1739.0, "sale": 1742.85}, "arp": {"purchase": 541.37, "sale": 542.72}, "jpy": {"purchase": 39.0, "sale": 39.08}, "eur": {"purchase": 5684.04, "sale": 5694.94}, "gbp": {"purchase": 7248.38, "sale": 7262.15}}, "2014-12-21": {"usd": {"purchase": 4630.96, "sale": 4639.46}, "brl": {"purchase": 1739.0, "sale": 1742.85}, "arp": {"purchase": 541.37, "sale": 542.72}, "jpy": {"purchase": 39.0, "sale": 39.08}, "eur": {"purchase": 5684.04, "sale": 5694.94}, "gbp": {"purchase": 7248.38, "sale": 7262.15}}, "2014-12-22": {"usd": {"purchase": 4623.39, "sale": 4630.51}, "brl": {"purchase": 1741.85, "sale": 1745.19}, "arp": {"purchase": 540.48, "sale": 541.68}, "jpy": {"purchase": 38.67, "sale": 38.73}, "eur": {"purchase": 5658.57, "sale": 5667.74}, "gbp": {"purchase": 7224.51, "sale": 7236.1}}, "2014-12-23": {"usd": {"purchase": 4619.4, "sale": 4626.51}, "brl": {"purchase": 1739.76, "sale": 1743.29}, "arp": {"purchase": 539.98, "sale": 541.18}, "jpy": {"purchase": 38.52, "sale": 38.58}, "eur": {"purchase": 5662.92, "sale": 5672.1}, "gbp": {"purchase": 7218.27, "sale": 7229.85}}, "2014-12-24": {"usd": {"purchase": 4615.99, "sale": 4621.11}, "brl": {"purchase": 1709.37, "sale": 1712.22}, "arp": {"purchase": 539.55, "sale": 540.52}, "jpy": {"purchase": 38.24, "sale": 38.28}, "eur": {"purchase": 5620.43, "sale": 5627.13}, "gbp": {"purchase": 7159.86, "sale": 7168.27}}, "2014-12-25": {"usd": {"purchase": 4615.99, "sale": 4621.11}, "brl": {"purchase": 1709.37, "sale": 1712.22}, "arp": {"purchase": 539.55, "sale": 540.52}, "jpy": {"purchase": 38.24, "sale": 38.28}, "eur": {"purchase": 5620.43, "sale": 5627.13}, "gbp": {"purchase": 7159.86, "sale": 7168.27}}, "2014-12-26": {"usd": {"purchase": 4617.45, "sale": 4630.25}, "brl": {"purchase": 1712.7, "sale": 1720.58}, "arp": {"purchase": 539.6, "sale": 541.35}, "jpy": {"purchase": 38.31, "sale": 38.42}, "eur": {"purchase": 5627.75, "sale": 5643.81}, "gbp": {"purchase": 7180.6, "sale": 7200.96}}, "2014-12-27": {"usd": {"purchase": 4617.45, "sale": 4630.25}, "brl": {"purchase": 1712.7, "sale": 1720.58}, "arp": {"purchase": 539.6, "sale": 541.35}, "jpy": {"purchase": 38.31, "sale": 38.42}, "eur": {"purchase": 5627.75, "sale": 5643.81}, "gbp": {"purchase": 7180.6, "sale": 7200.96}}, "2014-12-28": {"usd": {"purchase": 4617.45, "sale": 4630.25}, "brl": {"purchase": 1712.7, "sale": 1720.58}, "arp": {"purchase": 539.6, "sale": 541.35}, "jpy": {"purchase": 38.31, "sale": 38.42}, "eur": {"purchase": 5627.75, "sale": 5643.81}, "gbp": {"purchase": 7180.6, "sale": 7200.96}}, "2014-12-29": {"usd": {"purchase": 4616.05, "sale": 4621.91}, "brl": {"purchase": 1723.82, "sale": 1726.91}, "arp": {"purchase": 539.66, "sale": 540.71}, "jpy": {"purchase": 38.33, "sale": 38.38}, "eur": {"purchase": 5619.12, "sale": 5626.71}, "gbp": {"purchase": 7180.73, "sale": 7190.31}}, "2014-12-30": {"usd": {"purchase": 4622.56, "sale": 4629.95}, "brl": {"purchase": 1721.56, "sale": 1725.34}, "arp": {"purchase": 540.33, "sale": 541.57}, "jpy": {"purchase": 38.33, "sale": 38.39}, "eur": {"purchase": 5630.74, "sale": 5640.21}, "gbp": {"purchase": 7178.84, "sale": 7190.78}}, "2014-12-31": {"usd": {"purchase": 4629.3, "sale": 4642.16}, "brl": {"purchase": 1738.31, "sale": 1743.99}, "arp": {"purchase": 541.22, "sale": 542.98}, "jpy": {"purchase": 38.76, "sale": 38.87}, "eur": {"purchase": 5634.78, "sale": 5650.9}, "gbp": {"purchase": 7205.97, "sale": 7226.45}}}