{"2014-03-01": {"usd": {"purchase": 4430.41, "sale": 4432.39}, "brl": {"purchase": 1898.77, "sale": 1900.03}, "arp": {"purchase": 561.24, "sale": 561.7}, "jpy": {"purchase": 43.36, "sale": 43.38}, "eur": {"purchase": 6074.54, "sale": 6077.69}, "gbp": {"purchase": 7389.92, "sale": 7395.0}}, "2014-03-02": {"usd": {"purchase": 4430.41, "sale": 4432.39}, "brl": {"purchase": 1898.77, "sale": 1900.03}, "arp": {"purchase": 561.24, "sale": 561.7}, "jpy": {"purchase": 43.36, "sale": 43.38}, "eur": {"purchase": 6074.54, "sale": 6077.69}, "gbp": {"purchase": 7389.92, "sale": 7395.0}}, "2014-03-03": {"usd": {"purchase": 4432.96, "sale": 4439.56}, "brl": {"purchase": 1902.15, "sale": 1905.39}, "arp": {"purchase": 563.09, "sale": 564.11}, "jpy": {"purchase": 43.41, "sale": 43.48}, "eur": {"purchase": 6119.7, "sale": 6129.26}, "gbp": {"purchase": 7422.99, "sale": 7435.38}}, "2014-03-04": {"usd": {"purchase": 4419.73, "sale": 4422.94}, "brl": {"purchase": 1885.31, "sale": 1887.08}, "arp": {"purchase": 563.09, "sale": 560.99}, "jpy": {"purchase": 43.57, "sale": 43.61}, "eur": {"purchase": 6081.11, "sale": 6086.41}, "gbp": {"purchase": 7381.83, "sale": 7387.64}}, "2014-03-05": {"usd": {"purchase": 4411.05, "sale": 4416.84}, "brl": {"purchase": 1883.62, "sale": 1887.05}, "arp": {"purchase": 559.35, "sale": 560.23}, "jpy": {"purchase": 43.16, "sale": 43.23}, "eur": {"purchase": 6058.14, "sale": 6066.97}, "gbp": {"purchase": 7350.13, "sale": 7361.11}}, "2014-03-06": {"usd": {"purchase": 4425.23, "sale": 4431.52}, "brl": {"purchase": 1896.15, "sale": 1899.58}, "arp": {"purchase": 560.87, "sale": 562.02}, "jpy": {"purchase": 43.27, "sale": 43.33}, "eur": {"purchase": 6077.17, "sale": 6087.14}, "gbp": {"purchase": 7402.08, "sale": 7413.05}}, "2014-03-07": {"usd": {"purchase": 4427.78, "sale": 4433.99}, "brl": {"purchase": 1922.11, "sale": 1925.23}, "arp": {"purchase": 562.4, "sale": 563.26}, "jpy": {"purchase": 42.98, "sale": 43.04}, "eur": {"purchase": 6136.9, "sale": 6147.28}, "gbp": {"purchase": 7422.73, "sale": 7434.03}}, "2014-03-08": {"usd": {"purchase": 4427.78, "sale": 4433.99}, "brl": {"purchase": 1922.11, "sale": 1925.23}, "arp": {"purchase": 562.4, "sale": 563.26}, "jpy": {"purchase": 42.98, "sale": 43.04}, "eur": {"purchase": 6136.9, "sale": 6147.28}, "gbp": {"purchase": 7422.73, "sale": 7434.03}}, "2014-03-09": {"usd": {"purchase": 4427.78, "sale": 4433.99}, "brl": {"purchase": 1922.11, "sale": 1925.23}, "arp": {"purchase": 562.4, "sale": 563.26}, "jpy": {"purchase": 42.98, "sale": 43.04}, "eur": {"purchase": 6136.9, "sale": 6147.28}, "gbp": {"purchase": 7422.73, "sale": 7434.03}}, "2014-03-10": {"usd": {"purchase": 4423.91, "sale": 4428.14}, "brl": {"purchase": 1892.99, "sale": 1895.2}, "arp": {"purchase": 562.65, "sale": 563.61}, "jpy": {"purchase": 42.8, "sale": 42.84}, "eur": {"purchase": 6132.87, "sale": 6139.17}, "gbp": {"purchase": 7396.78, "sale": 7404.29}}, "2014-03-11": {"usd": {"purchase": 4419.12, "sale": 4425.94}, "brl": {"purchase": 1882.32, "sale": 1886.11}, "arp": {"purchase": 562.05, "sale": 563.1}, "jpy": {"purchase": 42.78, "sale": 42.86}, "eur": {"purchase": 6131.97, "sale": 6141.88}, "gbp": {"purchase": 7351.65, "sale": 7363.88}}, "2014-03-12": {"usd": {"purchase": 4411.69, "sale": 4415.81}, "brl": {"purchase": 1871.26, "sale": 1874.04}, "arp": {"purchase": 560.56, "sale": 561.55}, "jpy": {"purchase": 42.82, "sale": 42.86}, "eur": {"purchase": 6115.04, "sale": 6121.2}, "gbp": {"purchase": 7331.79, "sale": 7339.08}}, "2014-03-13": {"usd": {"purchase": 4417.93, "sale": 4425.78}, "brl": {"purchase": 1869.86, "sale": 1873.58}, "arp": {"purchase": 560.86, "sale": 562.33}, "jpy": {"purchase": 43.01, "sale": 43.09}, "eur": {"purchase": 6141.81, "sale": 6153.16}, "gbp": {"purchase": 7336.86, "sale": 7350.34}}, "2014-03-14": {"usd": {"purchase": 4414.4, "sale": 4417.43}, "brl": {"purchase": 1870.27, "sale": 1872.51}, "arp": {"purchase": 559.31, "sale": 560.15}, "jpy": {"purchase": 43.38, "sale": 43.41}, "eur": {"purchase": 6134.25, "sale": 6138.9}, "gbp": {"purchase": 7344.24, "sale": 7349.72}}, "2014-03-15": {"usd": {"purchase": 4414.4, "sale": 4417.43}, "brl": {"purchase": 1870.27, "sale": 1872.51}, "arp": {"purchase": 559.31, "sale": 560.15}, "jpy": {"purchase": 43.38, "sale": 43.41}, "eur": {"purchase": 6134.25, "sale": 6138.9}, "gbp": {"purchase": 7344.24, "sale": 7349.72}}, "2014-03-16": {"usd": {"purchase": 4414.4, "sale": 4417.43}, "brl": {"purchase": 1870.27, "sale": 1872.51}, "arp": {"purchase": 559.31, "sale": 560.15}, "jpy": {"purchase": 43.38, "sale": 43.41}, "eur": {"purchase": 6134.25, "sale": 6138.9}, "gbp": {"purchase": 7344.24, "sale": 7349.72}}, "2014-03-17": {"usd": {"purchase": 4414.96, "sale": 4421.13}, "brl": {"purchase": 1873.21, "sale": 1876.7}, "arp": {"purchase": 558.69, "sale": 559.93}, "jpy": {"purchase": 43.52, "sale": 43.59}, "eur": {"purchase": 6142.53, "sale": 6151.56}, "gbp": {"purchase": 7339.87, "sale": 7350.57}}, "2014-03-18": {"usd": {"purchase": 4414.27, "sale": 4419.97}, "brl": {"purchase": 1878.01, "sale": 1881.0}, "arp": {"purchase": 557.44, "sale": 558.44}, "jpy": {"purchase": 43.43, "sale": 43.49}, "eur": {"purchase": 6145.99, "sale": 6154.37}, "gbp": {"purchase": 7345.79, "sale": 7355.71}}, "2014-03-19": {"usd": {"purchase": 4404.4, "sale": 4409.89}, "brl": {"purchase": 1877.25, "sale": 1880.47}, "arp": {"purchase": 554.09, "sale": 555.15}, "jpy": {"purchase": 43.46, "sale": 43.52}, "eur": {"purchase": 6126.96, "sale": 6135.04}, "gbp": {"purchase": 7298.09, "sale": 7307.63}}, "2014-03-20": {"usd": {"purchase": 4400.3, "sale": 4406.95}, "brl": {"purchase": 1890.65, "sale": 1894.16}, "arp": {"purchase": 553.25, "sale": 554.54}, "jpy": {"purchase": 43.32, "sale": 43.39}, "eur": {"purchase": 6122.14, "sale": 6131.83}, "gbp": {"purchase": 7315.94, "sale": 7327.44}}, "2014-03-21": {"usd": {"purchase": 4412.63, "sale": 4418.72}, "brl": {"purchase": 1895.46, "sale": 1898.56}, "arp": {"purchase": 554.23, "sale": 555.45}, "jpy": {"purchase": 43.08, "sale": 43.14}, "eur": {"purchase": 6083.69, "sale": 6092.53}, "gbp": {"purchase": 7287.46, "sale": 7297.96}}, "2014-03-22": {"usd": {"purchase": 4412.63, "sale": 4418.72}, "brl": {"purchase": 1895.46, "sale": 1898.56}, "arp": {"purchase": 554.23, "sale": 555.45}, "jpy": {"purchase": 43.08, "sale": 43.14}, "eur": {"purchase": 6083.69, "sale": 6092.53}, "gbp": {"purchase": 7287.46, "sale": 7297.96}}, "2014-03-23": {"usd": {"purchase": 4412.63, "sale": 4418.72}, "brl": {"purchase": 1895.46, "sale": 1898.56}, "arp": {"purchase": 554.23, "sale": 555.45}, "jpy": {"purchase": 43.08, "sale": 43.14}, "eur": {"purchase": 6083.69, "sale": 6092.53}, "gbp": {"purchase": 7287.46, "sale": 7297.96}}, "2014-03-24": {"usd": {"purchase": 4419.93, "sale": 4428.28}, "brl": {"purchase": 1903.75, "sale": 1908.41}, "arp": {"purchase": 554.43, "sale": 555.71}, "jpy": {"purchase": 43.21, "sale": 43.3}, "eur": {"purchase": 6099.06, "sale": 6111.03}, "gbp": {"purchase": 7291.56, "sale": 7305.78}}, "2014-03-25": {"usd": {"purchase": 4432.74, "sale": 4439.46}, "brl": {"purchase": 1908.28, "sale": 1913.15}, "arp": {"purchase": 555.68, "sale": 556.99}, "jpy": {"purchase": 43.37, "sale": 43.44}, "eur": {"purchase": 6140.23, "sale": 6149.98}, "gbp": {"purchase": 7322.44, "sale": 7333.99}}, "2014-03-26": {"usd": {"purchase": 4431.44, "sale": 4433.85}, "brl": {"purchase": 1924.7, "sale": 1926.59}, "arp": {"purchase": 553.34, "sale": 554.09}, "jpy": {"purchase": 43.33, "sale": 43.35}, "eur": {"purchase": 6126.91, "sale": 6130.68}, "gbp": {"purchase": 7324.28, "sale": 7328.71}}, "2014-03-27": {"usd": {"purchase": 4425.62, "sale": 4432.53}, "brl": {"purchase": 1912.71, "sale": 1916.69}, "arp": {"purchase": 552.79, "sale": 554.07}, "jpy": {"purchase": 43.29, "sale": 43.36}, "eur": {"purchase": 6105.14, "sale": 6115.12}, "gbp": {"purchase": 7332.81, "sale": 7344.7}}, "2014-03-28": {"usd": {"purchase": 4434.3, "sale": 4441.33}, "brl": {"purchase": 1952.75, "sale": 1956.79}, "arp": {"purchase": 554.02, "sale": 555.37}, "jpy": {"purchase": 43.41, "sale": 43.49}, "eur": {"purchase": 6096.28, "sale": 6106.38}, "gbp": {"purchase": 7370.25, "sale": 7382.38}}, "2014-03-29": {"usd": {"purchase": 4434.3, "sale": 4441.33}, "brl": {"purchase": 1952.75, "sale": 1956.79}, "arp": {"purchase": 554.02, "sale": 555.37}, "jpy": {"purchase": 43.41, "sale": 43.49}, "eur": {"purchase": 6096.28, "sale": 6106.38}, "gbp": {"purchase": 7370.25, "sale": 7382.38}}, "2014-03-30": {"usd": {"purchase": 4434.3, "sale": 4441.33}, "brl": {"purchase": 1952.75, "sale": 1956.79}, "arp": {"purchase": 554.02, "sale": 555.37}, "jpy": {"purchase": 43.41, "sale": 43.49}, "eur": {"purchase": 6096.28, "sale": 6106.38}, "gbp": {"purchase": 7370.25, "sale": 7382.38}}, "2014-03-31": {"usd": {"purchase": 4437.23, "sale": 4445.35}, "brl": {"purchase": 1961.99, "sale": 1966.53}, "arp": {"purchase": 554.29, "sale": 555.77}, "jpy": {"purchase": 43.14, "sale": 43.23}, "eur": {"purchase": 6100.75, "sale": 6112.36}, "gbp": {"purchase": 7380.44, "sale": 7394.4}}}