{"2024-06-01": {"usd": {"purchase": 7521.21, "sale": 7522.66}, "brl": {"purchase": 1435.1, "sale": 1435.68}, "arp": {"purchase": 8.4, "sale": 8.4}, "jpy": {"purchase": 47.83, "sale": 47.84}, "eur": {"purchase": 8153.74, "sale": 8156.07}, "gbp": {"purchase": 9569.99, "sale": 9572.59}}, "2024-06-02": {"usd": {"purchase": 7521.21, "sale": 7522.66}, "brl": {"purchase": 1435.1, "sale": 1435.68}, "arp": {"purchase": 8.4, "sale": 8.4}, "jpy": {"purchase": 47.83, "sale": 47.84}, "eur": {"purchase": 8153.74, "sale": 8156.07}, "gbp": {"purchase": 9569.99, "sale": 9572.59}}, "2024-06-03": {"usd": {"purchase": 7520.03, "sale": 7533.79}, "brl": {"purchase": 1436.03, "sale": 1439.06}, "arp": {"purchase": 8.39, "sale": 8.41}, "jpy": {"purchase": 48.19, "sale": 48.28}, "eur": {"purchase": 8188.56, "sale": 8204.29}, "gbp": {"purchase": 9619.63, "sale": 9637.97}}}