{"2022-10-01": {"usd": {"purchase": 7078.87, "sale": 7090.2}, "brl": {"purchase": 1306.91, "sale": 1309.22}, "arp": {"purchase": 48.05, "sale": 48.13}, "jpy": {"purchase": 48.91, "sale": 48.99}, "eur": {"purchase": 6923.13, "sale": 6934.22}, "gbp": {"purchase": 7865.33, "sale": 7879.34}}, "2022-10-02": {"usd": {"purchase": 7078.87, "sale": 7090.2}, "brl": {"purchase": 1306.91, "sale": 1309.22}, "arp": {"purchase": 48.05, "sale": 48.13}, "jpy": {"purchase": 48.91, "sale": 48.99}, "eur": {"purchase": 6923.13, "sale": 6934.22}, "gbp": {"purchase": 7865.33, "sale": 7879.34}}, "2022-10-03": {"usd": {"purchase": 7078.87, "sale": 7090.2}, "brl": {"purchase": 1306.91, "sale": 1309.22}, "arp": {"purchase": 48.05, "sale": 48.13}, "jpy": {"purchase": 48.91, "sale": 48.99}, "eur": {"purchase": 6923.13, "sale": 6934.22}, "gbp": {"purchase": 7865.33, "sale": 7879.34}}, "2022-10-04": {"usd": {"purchase": 7053.97, "sale": 7064.27}, "brl": {"purchase": 1371.91, "sale": 1374.16}, "arp": {"purchase": 47.48, "sale": 47.55}, "jpy": {"purchase": 48.87, "sale": 48.94}, "eur": {"purchase": 7029.28, "sale": 7040.25}, "gbp": {"purchase": 8058.45, "sale": 8071.64}}, "2022-10-05": {"usd": {"purchase": 7061.19, "sale": 7070.87}, "brl": {"purchase": 1350.16, "sale": 1352.24}, "arp": {"purchase": 47.41, "sale": 47.48}, "jpy": {"purchase": 48.77, "sale": 48.84}, "eur": {"purchase": 6962.34, "sale": 6972.58}, "gbp": {"purchase": 7943.84, "sale": 7955.44}}, "2022-10-06": {"usd": {"purchase": 7086.18, "sale": 7094.11}, "brl": {"purchase": 1362.02, "sale": 1363.81}, "arp": {"purchase": 47.49, "sale": 47.55}, "jpy": {"purchase": 48.93, "sale": 48.99}, "eur": {"purchase": 6968.55, "sale": 6977.06}, "gbp": {"purchase": 7921.65, "sale": 7931.92}}, "2022-10-07": {"usd": {"purchase": 7113.67, "sale": 7121.81}, "brl": {"purchase": 1364.26, "sale": 1366.24}, "arp": {"purchase": 47.68, "sale": 47.74}, "jpy": {"purchase": 48.99, "sale": 49.05}, "eur": {"purchase": 6955.75, "sale": 6964.42}, "gbp": {"purchase": 7899.02, "sale": 7908.77}}, "2022-10-08": {"usd": {"purchase": 7113.67, "sale": 7121.81}, "brl": {"purchase": 1364.26, "sale": 1366.24}, "arp": {"purchase": 47.68, "sale": 47.74}, "jpy": {"purchase": 48.99, "sale": 49.05}, "eur": {"purchase": 6955.75, "sale": 6964.42}, "gbp": {"purchase": 7899.02, "sale": 7908.77}}, "2022-10-09": {"usd": {"purchase": 7113.67, "sale": 7121.81}, "brl": {"purchase": 1364.26, "sale": 1366.24}, "arp": {"purchase": 47.68, "sale": 47.74}, "jpy": {"purchase": 48.99, "sale": 49.05}, "eur": {"purchase": 6955.75, "sale": 6964.42}, "gbp": {"purchase": 7899.02, "sale": 7908.77}}, "2022-10-10": {"usd": {"purchase": 7098.8, "sale": 7102.97}, "brl": {"purchase": 1360.97, "sale": 1361.9}, "arp": {"purchase": 47.58, "sale": 47.62}, "jpy": {"purchase": 48.7, "sale": 48.73}, "eur": {"purchase": 6885.13, "sale": 6889.88}, "gbp": {"purchase": 7836.37, "sale": 7841.68}}, "2022-10-11": {"usd": {"purchase": 7115.2, "sale": 7121.61}, "brl": {"purchase": 1364.08, "sale": 1365.52}, "arp": {"purchase": 47.2, "sale": 47.25}, "jpy": {"purchase": 48.82, "sale": 48.87}, "eur": {"purchase": 6909.57, "sale": 6916.51}, "gbp": {"purchase": 7890.04, "sale": 7897.87}}, "2022-10-12": {"usd": {"purchase": 7119.67, "sale": 7140.49}, "brl": {"purchase": 1342.52, "sale": 1346.93}, "arp": {"purchase": 47.14, "sale": 47.29}, "jpy": {"purchase": 48.46, "sale": 48.6}, "eur": {"purchase": 6910.35, "sale": 6931.27}, "gbp": {"purchase": 7886.46, "sale": 7910.94}}, "2022-10-13": {"usd": {"purchase": 7155.4, "sale": 7156.32}, "brl": {"purchase": 1355.21, "sale": 1355.7}, "arp": {"purchase": 47.29, "sale": 47.3}, "jpy": {"purchase": 48.57, "sale": 48.58}, "eur": {"purchase": 6972.22, "sale": 6973.83}, "gbp": {"purchase": 8079.16, "sale": 8081.63}}, "2022-10-14": {"usd": {"purchase": 7142.92, "sale": 7148.6}, "brl": {"purchase": 1347.95, "sale": 1349.35}, "arp": {"purchase": 47.11, "sale": 47.15}, "jpy": {"purchase": 48.12, "sale": 48.16}, "eur": {"purchase": 6968.64, "sale": 6974.89}, "gbp": {"purchase": 8024.36, "sale": 8032.17}}, "2022-10-15": {"usd": {"purchase": 7142.92, "sale": 7148.6}, "brl": {"purchase": 1347.95, "sale": 1349.35}, "arp": {"purchase": 47.11, "sale": 47.15}, "jpy": {"purchase": 48.12, "sale": 48.16}, "eur": {"purchase": 6968.64, "sale": 6974.89}, "gbp": {"purchase": 8024.36, "sale": 8032.17}}, "2022-10-16": {"usd": {"purchase": 7142.92, "sale": 7148.6}, "brl": {"purchase": 1347.95, "sale": 1349.35}, "arp": {"purchase": 47.11, "sale": 47.15}, "jpy": {"purchase": 48.12, "sale": 48.16}, "eur": {"purchase": 6968.64, "sale": 6974.89}, "gbp": {"purchase": 8024.36, "sale": 8032.17}}}