{"2019-05-01": {"usd": {"purchase": 6281.7, "sale": 6292.16}, "brl": {"purchase": 1593.94, "sale": 1596.79}, "arp": {"purchase": 141.64, "sale": 142.84}, "jpy": {"purchase": 56.39, "sale": 56.49}, "eur": {"purchase": 7035.5, "sale": 7047.22}, "gbp": {"purchase": 8183.17, "sale": 8196.8}}, "2019-05-02": {"usd": {"purchase": 6294.21, "sale": 6324.33}, "brl": {"purchase": 1587.84, "sale": 1595.64}, "arp": {"purchase": 140.08, "sale": 140.86}, "jpy": {"purchase": 56.51, "sale": 56.78}, "eur": {"purchase": 7037.56, "sale": 7071.87}, "gbp": {"purchase": 8200.1, "sale": 8239.97}}, "2019-05-03": {"usd": {"purchase": 6318.55, "sale": 6320.8}, "brl": {"purchase": 1603.29, "sale": 1604.26}, "arp": {"purchase": 142.44, "sale": 142.69}, "jpy": {"purchase": 56.79, "sale": 56.81}, "eur": {"purchase": 7067.93, "sale": 7070.45}, "gbp": {"purchase": 8304.47, "sale": 8308.06}}, "2019-05-04": {"usd": {"purchase": 6318.55, "sale": 6320.8}, "brl": {"purchase": 1603.29, "sale": 1604.26}, "arp": {"purchase": 142.44, "sale": 142.69}, "jpy": {"purchase": 56.79, "sale": 56.81}, "eur": {"purchase": 7067.93, "sale": 7070.45}, "gbp": {"purchase": 8304.47, "sale": 8308.06}}, "2019-05-05": {"usd": {"purchase": 6318.55, "sale": 6320.8}, "brl": {"purchase": 1603.29, "sale": 1604.26}, "arp": {"purchase": 142.44, "sale": 142.69}, "jpy": {"purchase": 56.79, "sale": 56.81}, "eur": {"purchase": 7067.93, "sale": 7070.45}, "gbp": {"purchase": 8304.47, "sale": 8308.06}}, "2019-05-06": {"usd": {"purchase": 6332.81, "sale": 6344.5}, "brl": {"purchase": 1601.38, "sale": 1604.62}, "arp": {"purchase": 141.4, "sale": 141.81}, "jpy": {"purchase": 57.11, "sale": 57.22}, "eur": {"purchase": 7089.58, "sale": 7102.67}, "gbp": {"purchase": 8290.28, "sale": 8306.22}}, "2019-05-07": {"usd": {"purchase": 6347.46, "sale": 6354.04}, "brl": {"purchase": 1593.28, "sale": 1595.17}, "arp": {"purchase": 141.39, "sale": 141.62}, "jpy": {"purchase": 57.51, "sale": 57.57}, "eur": {"purchase": 7098.36, "sale": 7106.36}, "gbp": {"purchase": 8286.61, "sale": 8295.83}}, "2019-05-08": {"usd": {"purchase": 6355.13, "sale": 6366.79}, "brl": {"purchase": 1616.96, "sale": 1620.21}, "arp": {"purchase": 141.04, "sale": 141.37}, "jpy": {"purchase": 57.73, "sale": 57.84}, "eur": {"purchase": 7124.74, "sale": 7137.81}, "gbp": {"purchase": 8271.84, "sale": 8287.65}}, "2019-05-09": {"usd": {"purchase": 6355.5, "sale": 6373.99}, "brl": {"purchase": 1599.39, "sale": 1604.21}, "arp": {"purchase": 139.09, "sale": 139.57}, "jpy": {"purchase": 57.73, "sale": 58.05}, "eur": {"purchase": 7139.13, "sale": 7137.81}, "gbp": {"purchase": 8272.95, "sale": 8297.66}}, "2019-05-10": {"usd": {"purchase": 6383.48, "sale": 6407.94}, "brl": {"purchase": 1608.78, "sale": 1615.15}, "arp": {"purchase": 141.73, "sale": 142.4}, "jpy": {"purchase": 58.26, "sale": 58.48}, "eur": {"purchase": 7177.58, "sale": 7205.09}, "gbp": {"purchase": 8317.04, "sale": 8349.55}}, "2019-05-11": {"usd": {"purchase": 6383.48, "sale": 6407.94}, "brl": {"purchase": 1608.78, "sale": 1615.15}, "arp": {"purchase": 141.73, "sale": 142.4}, "jpy": {"purchase": 58.26, "sale": 58.48}, "eur": {"purchase": 7177.58, "sale": 7205.09}, "gbp": {"purchase": 8317.04, "sale": 8349.55}}, "2019-05-12": {"usd": {"purchase": 6383.48, "sale": 6407.94}, "brl": {"purchase": 1608.78, "sale": 1615.15}, "arp": {"purchase": 141.73, "sale": 142.4}, "jpy": {"purchase": 58.26, "sale": 58.48}, "eur": {"purchase": 7177.58, "sale": 7205.09}, "gbp": {"purchase": 8317.04, "sale": 8349.55}}, "2019-05-13": {"usd": {"purchase": 6339.4, "sale": 6362.54}, "brl": {"purchase": 1591.02, "sale": 1597.18}, "arp": {"purchase": 139.8, "sale": 140.45}, "jpy": {"purchase": 58.1, "sale": 58.31}, "eur": {"purchase": 7122.32, "sale": 7148.95}, "gbp": {"purchase": 8214.6, "sale": 8245.22}}, "2019-05-14": {"usd": {"purchase": 6339.4, "sale": 6362.54}, "brl": {"purchase": 1591.02, "sale": 1597.18}, "arp": {"purchase": 139.8, "sale": 140.45}, "jpy": {"purchase": 58.1, "sale": 58.31}, "eur": {"purchase": 7122.32, "sale": 7148.95}, "gbp": {"purchase": 8214.6, "sale": 8245.22}}, "2019-05-15": {"usd": {"purchase": 6339.4, "sale": 6362.54}, "brl": {"purchase": 1591.02, "sale": 1597.18}, "arp": {"purchase": 139.8, "sale": 140.45}, "jpy": {"purchase": 58.1, "sale": 58.31}, "eur": {"purchase": 7122.32, "sale": 7148.95}, "gbp": {"purchase": 8214.6, "sale": 8245.22}}, "2019-05-16": {"usd": {"purchase": 6283.45, "sale": 6301.67}, "brl": {"purchase": 1564.76, "sale": 1569.49}, "arp": {"purchase": 140.3, "sale": 140.89}, "jpy": {"purchase": 57.21, "sale": 57.38}, "eur": {"purchase": 7023.64, "sale": 7044.64}, "gbp": {"purchase": 8042.82, "sale": 8066.77}}, "2019-05-17": {"usd": {"purchase": 6277.36, "sale": 6290.2}, "brl": {"purchase": 1531.66, "sale": 1535.02}, "arp": {"purchase": 139.39, "sale": 139.93}, "jpy": {"purchase": 57.14, "sale": 57.26}, "eur": {"purchase": 7009.93, "sale": 7024.9}, "gbp": {"purchase": 7991.08, "sale": 8008.06}}, "2019-05-18": {"usd": {"purchase": 6277.36, "sale": 6290.2}, "brl": {"purchase": 1531.66, "sale": 1535.02}, "arp": {"purchase": 139.39, "sale": 139.93}, "jpy": {"purchase": 57.14, "sale": 57.26}, "eur": {"purchase": 7009.93, "sale": 7024.9}, "gbp": {"purchase": 7991.08, "sale": 8008.06}}, "2019-05-19": {"usd": {"purchase": 6277.36, "sale": 6290.2}, "brl": {"purchase": 1531.66, "sale": 1535.02}, "arp": {"purchase": 139.39, "sale": 139.93}, "jpy": {"purchase": 57.14, "sale": 57.26}, "eur": {"purchase": 7009.93, "sale": 7024.9}, "gbp": {"purchase": 7991.08, "sale": 8008.06}}, "2019-05-20": {"usd": {"purchase": 6283.97, "sale": 6308.24}, "brl": {"purchase": 1527.76, "sale": 1533.99}, "arp": {"purchase": 138.4, "sale": 139.08}, "jpy": {"purchase": 57.15, "sale": 57.37}, "eur": {"purchase": 7019.82, "sale": 7047.56}, "gbp": {"purchase": 7992.58, "sale": 8024.08}}, "2019-05-21": {"usd": {"purchase": 6313.63, "sale": 6326.6}, "brl": {"purchase": 1553.02, "sale": 1556.4}, "arp": {"purchase": 140.69, "sale": 141.17}, "jpy": {"purchase": 57.06, "sale": 57.18}, "eur": {"purchase": 7047.28, "sale": 7061.75}, "gbp": {"purchase": 8037.89, "sale": 8055.66}}, "2019-05-22": {"usd": {"purchase": 6332.78, "sale": 6349.59}, "brl": {"purchase": 1570.16, "sale": 1574.76}, "arp": {"purchase": 141.68, "sale": 142.1}, "jpy": {"purchase": 57.42, "sale": 57.57}, "eur": {"purchase": 7064.85, "sale": 7083.6}, "gbp": {"purchase": 8.023, "sale": 8044.93}}, "2019-05-23": {"usd": {"purchase": 6289.2, "sale": 6303.9}, "brl": {"purchase": 1558.12, "sale": 1561.96}, "arp": {"purchase": 139.53, "sale": 139.95}, "jpy": {"purchase": 57.37, "sale": 57.51}, "eur": {"purchase": 7025.67, "sale": 7042.72}, "gbp": {"purchase": 7965.27, "sale": 7985.15}}, "2019-05-24": {"usd": {"purchase": 6279.53, "sale": 6291.32}, "brl": {"purchase": 1561.88, "sale": 1565.2}, "arp": {"purchase": 139.59, "sale": 139.93}, "jpy": {"purchase": 57.42, "sale": 57.53}, "eur": {"purchase": 7033.7, "sale": 7047.54}, "gbp": {"purchase": 7969.98, "sale": 7985.57}}, "2019-05-25": {"usd": {"purchase": 6279.53, "sale": 6291.32}, "brl": {"purchase": 1561.88, "sale": 1565.2}, "arp": {"purchase": 139.59, "sale": 139.93}, "jpy": {"purchase": 57.42, "sale": 57.53}, "eur": {"purchase": 7033.7, "sale": 7047.54}, "gbp": {"purchase": 7969.98, "sale": 7985.57}}, "2019-05-26": {"usd": {"purchase": 6279.53, "sale": 6291.32}, "brl": {"purchase": 1561.88, "sale": 1565.2}, "arp": {"purchase": 139.59, "sale": 139.93}, "jpy": {"purchase": 57.42, "sale": 57.53}, "eur": {"purchase": 7033.7, "sale": 7047.54}, "gbp": {"purchase": 7969.98, "sale": 7985.57}}, "2019-05-27": {"usd": {"purchase": 6260.15, "sale": 6274.28}, "brl": {"purchase": 1556.55, "sale": 1560.45}, "arp": {"purchase": 139.27, "sale": 139.65}, "jpy": {"purchase": 57.15, "sale": 57.28}, "eur": {"purchase": 7006.36, "sale": 7022.17}, "gbp": {"purchase": 7934.74, "sale": 7953.27}}, "2019-05-28": {"usd": {"purchase": 6255.89, "sale": 6273.35}, "brl": {"purchase": 1553.29, "sale": 1557.82}, "arp": {"purchase": 139.69, "sale": 140.26}, "jpy": {"purchase": 57.1, "sale": 57.26}, "eur": {"purchase": 6987.83, "sale": 7007.96}, "gbp": {"purchase": 7918.7, "sale": 7941.44}}, "2019-05-29": {"usd": {"purchase": 6299.13, "sale": 6319.05}, "brl": {"purchase": 1577.54, "sale": 1583.13}, "arp": {"purchase": 141.86, "sale": 142.42}, "jpy": {"purchase": 57.62, "sale": 57.8}, "eur": {"purchase": 7012.19, "sale": 7034.36}, "gbp": {"purchase": 7949.5, "sale": 7975.27}}, "2019-05-30": {"usd": {"purchase": 6299.65, "sale": 6319.04}, "brl": {"purchase": 1589.26, "sale": 1594.47}, "arp": {"purchase": 142.12, "sale": 142.69}, "jpy": {"purchase": 57.44, "sale": 57.62}, "eur": {"purchase": 7016.55, "sale": 7038.78}, "gbp": {"purchase": 7947.01, "sale": 7972.1}}, "2019-05-31": {"usd": {"purchase": 6269.27, "sale": 6278.13}, "brl": {"purchase": 1599.06, "sale": 1601.64}, "arp": {"purchase": 139.52, "sale": 139.98}, "jpy": {"purchase": 57.73, "sale": 57.81}, "eur": {"purchase": 6993.37, "sale": 7003.88}, "gbp": {"purchase": 7913.7, "sale": 7925.51}}}